{"song":{"keyCount":8,"player1":"bf","modchartPath":"charfloatshag","chartOffset":0,"player2":"god-shaggy","notes":[{"sectionNotes":[],"lengthInSteps":16,"typeOfSection":0,"bpm":0.1,"mustHitSection":false},{"lengthInSteps":16,"typeOfSection":0,"sectionNotes":[],"altAnim":false,"bpm":150,"changeBPM":false,"mustHitSection":false},{"lengthInSteps":16,"typeOfSection":0,"sectionNotes":[],"altAnim":false,"bpm":150,"changeBPM":false,"mustHitSection":true},{"lengthInSteps":16,"typeOfSection":0,"sectionNotes":[],"altAnim":false,"bpm":150,"changeBPM":false,"mustHitSection":true},{"lengthInSteps":16,"typeOfSection":0,"sectionNotes":[[6600,4,0,0,"default"],[6800,6,0,0,"default"],[6900,5,0,0,"default"],[6400,2,100,0,"default"],[7000,2,100,0,"default"],[7200,7,0,0,"default"],[7400,4,0,0,"default"],[7600,1,0,0,"default"],[7700,5,0,0,"default"],[7800,3,0,0,"default"],[7900,0,0,0,"default"]],"altAnim":false,"bpm":150,"changeBPM":false,"mustHitSection":false},{"lengthInSteps":16,"typeOfSection":0,"sectionNotes":[[8000,4,0,0,"default"],[8100,6,0,0,"default"],[8200,4,0,0,"default"],[8400,2,100,0,"default"],[8600,1,100,0,"default"],[8800,7,0,0,"default"],[8900,5,0,0,"default"],[9000,4,0,0,"default"],[9100,2,0,0,"default"],[9200,6,0,0,"default"],[9300,3,0,0,"default"],[9400,1,0,0,"default"],[9500,0,0,0,"default"]],"altAnim":false,"bpm":150,"changeBPM":false,"mustHitSection":false},{"lengthInSteps":16,"typeOfSection":0,"sectionNotes":[[9800,4,0,0,"default"],[10000,6,0,0,"default"],[10100,5,0,0,"default"],[9600,2,100,0,"default"],[10200,2,100,0,"default"],[10400,7,0,0,"default"],[10600,4,0,0,"default"],[10800,1,0,0,"default"],[10900,5,0,0,"default"],[11000,3,0,0,"default"],[11100,0,0,0,"default"],[9600,9,700,0,"default"]],"altAnim":false,"bpm":150,"changeBPM":false,"mustHitSection":true},{"lengthInSteps":16,"typeOfSection":0,"sectionNotes":[[11200,4,0,0,"default"],[11300,6,0,0,"default"],[11400,4,0,0,"default"],[11600,2,100,0,"default"],[11800,1,100,0,"default"],[12000,7,0,0,"default"],[12100,5,0,0,"default"],[12200,4,0,0,"default"],[12300,2,0,0,"default"],[12400,6,0,0,"default"],[12500,3,0,0,"default"],[12600,1,0,0,"default"],[12700,0,0,0,"default"]],"altAnim":false,"bpm":150,"changeBPM":false,"mustHitSection":true},{"lengthInSteps":16,"typeOfSection":0,"sectionNotes":[[12800,9,700,0,"default"],[12800,6,0,0,"default"],[12900,2,0,0,"default"],[13000,1,0,0,"default"],[13100,4,0,0,"default"],[13200,3,100,0,"default"],[13400,6,0,0,"default"],[13600,7,0,0,"default"],[13700,4,0,0,"default"],[13800,2,0,0,"default"],[13900,5,0,0,"default"],[14000,6,0,0,"default"],[14100,2,0,0,"default"],[14200,5,0,0,"default"],[14300,1,0,0,"default"]],"altAnim":false,"bpm":150,"changeBPM":false,"mustHitSection":false},{"lengthInSteps":16,"typeOfSection":0,"sectionNotes":[[14400,3,100,0,"default"],[14600,6,0,0,"default"],[14800,5,100,0,"default"],[15000,0,0,0,"default"],[15200,2,300,0,"default"],[15600,6,0,0,"default"],[15700,3,0,0,"default"],[15800,4,0,0,"default"],[15900,5,0,0,"default"]],"altAnim":false,"bpm":150,"changeBPM":false,"mustHitSection":false},{"lengthInSteps":16,"typeOfSection":0,"sectionNotes":[[16000,15,700,0,"default"],[16000,6,0,0,"default"],[16100,2,0,0,"default"],[16200,1,0,0,"default"],[16300,4,0,0,"default"],[16400,3,100,0,"default"],[16600,6,0,0,"default"],[16800,7,0,0,"default"],[16900,4,0,0,"default"],[17000,2,0,0,"default"],[17100,5,0,0,"default"],[17200,6,0,0,"default"],[17300,2,0,0,"default"],[17400,5,0,0,"default"],[17500,1,0,0,"default"]],"altAnim":false,"bpm":150,"changeBPM":false,"mustHitSection":true},{"lengthInSteps":16,"typeOfSection":0,"sectionNotes":[[17600,3,100,0,"default"],[17800,6,0,0,"default"],[18000,5,100,0,"default"],[18200,0,0,0,"default"],[18400,2,300,0,"default"],[18800,6,0,0,"default"],[18900,3,0,0,"default"],[19000,4,0,0,"default"],[19100,5,0,0,"default"]],"altAnim":false,"bpm":150,"changeBPM":false,"mustHitSection":true},{"lengthInSteps":16,"typeOfSection":0,"sectionNotes":[[19200,15,700,0,"default"],[19200,3,0,0,"default"],[19300,5,0,0,"default"],[19400,6,0,0,"default"],[19500,1,0,0,"default"],[19600,4,0,0,"default"],[19700,3,0,0,"default"],[19800,2,0,0,"default"],[19900,5,0,0,"default"],[20000,7,0,0,"default"],[20100,0,0,0,"default"],[20200,3,0,0,"default"],[20400,5,0,0,"default"],[20500,1,0,0,"default"],[20600,5,0,0,"default"],[20700,2,0,0,"default"]],"altAnim":false,"bpm":150,"changeBPM":false,"mustHitSection":false},{"lengthInSteps":16,"typeOfSection":0,"sectionNotes":[[20800,3,0,0,"default"],[20900,6,0,0,"default"],[21000,7,0,0,"default"],[21100,4,0,0,"default"],[21200,2,0,0,"default"],[21300,0,0,0,"default"],[21400,5,0,0,"default"],[21500,1,0,0,"default"],[21600,7,0,0,"default"],[21650,6,0,0,"default"],[21700,4,0,0,"default"],[21750,2,0,0,"default"],[21800,5,0,0,"default"],[21850,3,0,0,"default"],[21900,1,0,0,"default"],[21950,0,0,0,"default"],[22000,7,0,0,"default"],[22050,6,0,0,"default"],[22100,4,0,0,"default"],[22150,2,0,0,"default"],[22200,5,0,0,"default"],[22250,3,0,0,"default"],[22300,1,0,0,"default"],[22350,0,0,0,"default"]],"altAnim":false,"bpm":150,"changeBPM":false,"mustHitSection":false},{"lengthInSteps":16,"typeOfSection":0,"sectionNotes":[[22400,12,300,0,"default"],[22400,3,0,0,"default"],[22500,5,0,0,"default"],[22600,6,0,0,"default"],[22700,1,0,0,"default"],[22800,4,0,0,"default"],[22900,3,0,0,"default"],[23000,2,0,0,"default"],[23100,5,0,0,"default"],[23200,7,0,0,"default"],[23300,0,0,0,"default"],[23400,3,0,0,"default"],[23600,5,0,0,"default"],[23700,1,0,0,"default"],[23800,5,0,0,"default"],[23900,2,0,0,"default"]],"altAnim":false,"bpm":150,"changeBPM":false,"mustHitSection":true},{"lengthInSteps":16,"typeOfSection":0,"sectionNotes":[[24000,3,0,0,"default"],[24100,6,0,0,"default"],[24200,7,0,0,"default"],[24300,4,0,0,"default"],[24400,2,0,0,"default"],[24500,0,0,0,"default"],[24600,5,0,0,"default"],[24700,1,0,0,"default"],[24800,7,0,0,"default"],[24850,6,0,0,"default"],[24900,4,0,0,"default"],[24950,2,0,0,"default"],[25000,5,0,0,"default"],[25050,3,0,0,"default"],[25100,1,0,0,"default"],[25150,0,0,0,"default"],[25200,7,0,0,"default"],[25250,6,0,0,"default"],[25300,4,0,0,"default"],[25350,2,0,0,"default"],[25400,5,0,0,"default"],[25450,3,0,0,"default"],[25500,1,0,0,"default"],[25550,0,0,0,"default"]],"altAnim":false,"bpm":150,"changeBPM":false,"mustHitSection":true},{"lengthInSteps":16,"typeOfSection":0,"sectionNotes":[[25600,12,300,0,"default"],[25600,2,0,0,"default"],[25700,7,0,0,"default"],[25900,7,0,0,"default"],[25800,6,0,0,"default"],[26000,4,100,0,"default"],[26200,1,0,0,"default"],[26400,3,0,0,"default"],[26500,1,0,0,"default"],[26600,4,0,0,"default"],[26700,3,0,0,"default"],[26800,0,0,0,"default"],[26900,2,0,0,"default"],[27000,7,0,0,"default"],[27100,5,0,0,"default"]],"altAnim":false,"bpm":150,"changeBPM":false,"mustHitSection":false},{"lengthInSteps":16,"typeOfSection":0,"sectionNotes":[[27200,4,0,0,"default"],[27300,6,0,0,"default"],[27400,1,0,0,"default"],[27500,7,0,0,"default"],[27600,3,0,0,"default"],[27700,2,0,0,"default"],[27800,5,0,0,"default"],[27900,0,0,0,"default"],[28000,4,100,0,"default"],[28200,6,100,0,"default"],[28500,0,0,0,"default"],[28700,0,0,0,"default"],[28400,2,0,0,"default"],[28600,7,0,0,"default"]],"altAnim":false,"bpm":150,"changeBPM":false,"mustHitSection":false},{"lengthInSteps":16,"typeOfSection":0,"sectionNotes":[[28800,11,300,0,"default"],[28800,2,0,0,"default"],[28900,7,0,0,"default"],[29100,7,0,0,"default"],[29000,6,0,0,"default"],[29200,4,100,0,"default"],[29400,1,0,0,"default"],[29600,3,0,0,"default"],[29700,1,0,0,"default"],[29800,4,0,0,"default"],[29900,3,0,0,"default"],[30000,0,0,0,"default"],[30100,2,0,0,"default"],[30200,7,0,0,"default"],[30300,5,0,0,"default"]],"altAnim":false,"bpm":150,"changeBPM":false,"mustHitSection":true},{"lengthInSteps":16,"typeOfSection":0,"sectionNotes":[[30400,4,0,0,"default"],[30500,6,0,0,"default"],[30600,1,0,0,"default"],[30700,7,0,0,"default"],[30800,3,0,0,"default"],[30900,2,0,0,"default"],[31000,5,0,0,"default"],[31100,0,0,0,"default"],[31200,4,100,0,"default"],[31400,6,100,0,"default"],[31700,0,0,0,"default"],[31900,0,0,0,"default"],[31600,2,0,0,"default"],[31800,7,0,0,"default"]],"altAnim":false,"bpm":150,"changeBPM":false,"mustHitSection":true},{"lengthInSteps":16,"typeOfSection":0,"sectionNotes":[[32000,11,300,0,"default"]],"altAnim":false,"bpm":150,"changeBPM":false,"mustHitSection":false},{"lengthInSteps":16,"typeOfSection":0,"sectionNotes":[],"altAnim":false,"bpm":150,"changeBPM":false,"mustHitSection":true},{"lengthInSteps":16,"typeOfSection":0,"sectionNotes":[[35200,1,0,0,"default"],[35300,4,0,0,"default"],[35400,5,0,0,"default"],[35500,2,0,0,"default"],[35600,6,0,0,"default"],[35700,1,0,0,"default"],[35800,7,0,0,"default"],[35900,6,0,0,"default"],[36000,3,100,0,"default"],[36200,0,0,0,"default"],[36300,2,0,0,"default"],[36400,3,100,0,"default"],[36600,4,0,0,"default"],[36700,1,0,0,"default"]],"altAnim":false,"bpm":150,"changeBPM":false,"mustHitSection":false},{"lengthInSteps":16,"typeOfSection":0,"sectionNotes":[[36800,1,0,0,"default"],[36900,4,0,0,"default"],[37000,5,0,0,"default"],[37100,2,0,0,"default"],[37200,6,0,0,"default"],[37300,1,0,0,"default"],[37400,7,0,0,"default"],[37500,6,0,0,"default"],[37600,3,100,0,"default"],[37800,0,0,0,"default"],[37900,2,0,0,"default"],[38000,3,100,0,"default"],[38200,4,0,0,"default"],[38300,1,0,0,"default"]],"altAnim":false,"bpm":150,"changeBPM":false,"mustHitSection":true},{"lengthInSteps":16,"typeOfSection":0,"sectionNotes":[[38400,6,100,0,"default"],[38600,3,100,0,"default"],[38800,1,100,0,"default"],[39000,0,0,0,"default"],[39300,4,0,0,"default"],[39400,6,0,0,"default"],[39500,7,0,0,"default"],[39600,2,100,0,"default"]],"altAnim":false,"bpm":150,"changeBPM":false,"mustHitSection":false},{"lengthInSteps":16,"typeOfSection":0,"sectionNotes":[[40000,1,0,0,"default"],[40100,3,0,0,"default"],[40200,6,0,0,"default"],[40300,4,0,0,"default"],[40400,0,0,0,"default"],[40500,2,0,0,"default"],[40600,7,0,0,"default"],[40700,5,0,0,"default"],[40900,3,0,0,"default"],[41000,1,0,0,"default"],[41100,0,0,0,"default"],[41200,6,100,0,"default"]],"altAnim":false,"bpm":150,"changeBPM":false,"mustHitSection":false},{"lengthInSteps":16,"typeOfSection":0,"sectionNotes":[[41600,6,100,0,"default"],[41800,3,100,0,"default"],[42000,1,100,0,"default"],[42200,0,0,0,"default"],[42500,4,0,0,"default"],[42600,6,0,0,"default"],[42700,7,0,0,"default"],[42800,2,100,0,"default"]],"altAnim":false,"bpm":150,"changeBPM":false,"mustHitSection":true},{"lengthInSteps":16,"typeOfSection":0,"sectionNotes":[[43200,1,0,0,"default"],[43300,3,0,0,"default"],[43400,6,0,0,"default"],[43500,4,0,0,"default"],[43600,0,0,0,"default"],[43700,2,0,0,"default"],[43800,7,0,0,"default"],[43900,5,0,0,"default"],[44100,3,0,0,"default"],[44200,1,0,0,"default"],[44300,0,0,0,"default"],[44400,6,100,0,"default"]],"altAnim":false,"bpm":150,"changeBPM":false,"mustHitSection":true},{"lengthInSteps":16,"typeOfSection":0,"sectionNotes":[[45000,4,0,0,"default"],[45200,6,0,0,"default"],[45300,5,0,0,"default"],[44800,2,100,0,"default"],[45400,2,100,0,"default"],[45600,7,0,0,"default"],[45800,4,0,0,"default"],[46000,1,0,0,"default"],[46100,5,0,0,"default"],[46200,3,0,0,"default"],[46300,0,0,0,"default"]],"altAnim":false,"bpm":150,"changeBPM":false,"mustHitSection":false},{"lengthInSteps":16,"typeOfSection":0,"sectionNotes":[[46400,4,0,0,"default"],[46500,6,0,0,"default"],[46600,4,0,0,"default"],[46800,2,100,0,"default"],[47000,1,100,0,"default"],[47200,7,0,0,"default"],[47300,5,0,0,"default"],[47400,4,0,0,"default"],[47500,2,0,0,"default"],[47600,6,0,0,"default"],[47700,3,0,0,"default"],[47800,1,0,0,"default"],[47900,0,0,0,"default"]],"altAnim":false,"bpm":150,"changeBPM":false,"mustHitSection":false},{"lengthInSteps":16,"typeOfSection":0,"sectionNotes":[[48200,4,0,0,"default"],[48400,6,0,0,"default"],[48500,5,0,0,"default"],[48000,2,100,0,"default"],[48600,2,100,0,"default"],[48800,7,0,0,"default"],[49000,4,0,0,"default"],[49200,1,0,0,"default"],[49300,5,0,0,"default"],[49400,3,0,0,"default"],[49500,0,0,0,"default"],[48000,9,700,0,"default"]],"altAnim":false,"bpm":150,"changeBPM":false,"mustHitSection":true},{"lengthInSteps":16,"typeOfSection":0,"sectionNotes":[[49600,4,0,0,"default"],[49700,6,0,0,"default"],[49800,4,0,0,"default"],[50000,2,100,0,"default"],[50200,1,100,0,"default"],[50400,7,0,0,"default"],[50500,5,0,0,"default"],[50600,4,0,0,"default"],[50700,2,0,0,"default"],[50800,6,0,0,"default"],[50900,3,0,0,"default"],[51000,1,0,0,"default"],[51100,0,0,0,"default"]],"altAnim":false,"bpm":150,"changeBPM":false,"mustHitSection":true},{"lengthInSteps":16,"typeOfSection":0,"sectionNotes":[[51200,9,700,0,"default"],[51200,6,0,0,"default"],[51300,2,0,0,"default"],[51400,1,0,0,"default"],[51500,4,0,0,"default"],[51600,3,100,0,"default"],[51800,6,0,0,"default"],[52000,7,0,0,"default"],[52100,4,0,0,"default"],[52200,2,0,0,"default"],[52300,5,0,0,"default"],[52400,6,0,0,"default"],[52500,2,0,0,"default"],[52600,5,0,0,"default"],[52700,1,0,0,"default"]],"altAnim":false,"bpm":150,"changeBPM":false,"mustHitSection":false},{"lengthInSteps":16,"typeOfSection":0,"sectionNotes":[[52800,3,100,0,"default"],[53000,6,0,0,"default"],[53200,5,100,0,"default"],[53400,0,0,0,"default"],[53600,2,300,0,"default"],[54000,6,0,0,"default"],[54100,3,0,0,"default"],[54200,4,0,0,"default"],[54300,5,0,0,"default"]],"altAnim":false,"bpm":150,"changeBPM":false,"mustHitSection":false},{"lengthInSteps":16,"typeOfSection":0,"sectionNotes":[[54400,15,700,0,"default"],[54400,6,0,0,"default"],[54500,2,0,0,"default"],[54600,1,0,0,"default"],[54700,4,0,0,"default"],[54800,3,100,0,"default"],[55000,6,0,0,"default"],[55200,7,0,0,"default"],[55300,4,0,0,"default"],[55400,2,0,0,"default"],[55500,5,0,0,"default"],[55600,6,0,0,"default"],[55700,2,0,0,"default"],[55800,5,0,0,"default"],[55900,1,0,0,"default"]],"altAnim":false,"bpm":150,"changeBPM":false,"mustHitSection":true},{"lengthInSteps":16,"typeOfSection":0,"sectionNotes":[[56000,3,100,0,"default"],[56200,6,0,0,"default"],[56400,5,100,0,"default"],[56600,0,0,0,"default"],[56800,2,300,0,"default"],[57200,6,0,0,"default"],[57300,3,0,0,"default"],[57400,4,0,0,"default"],[57500,5,0,0,"default"]],"altAnim":false,"bpm":150,"changeBPM":false,"mustHitSection":true},{"lengthInSteps":16,"typeOfSection":0,"sectionNotes":[[57600,15,700,0,"default"],[57600,3,0,0,"default"],[57700,5,0,0,"default"],[57800,6,0,0,"default"],[57900,1,0,0,"default"],[58000,4,0,0,"default"],[58100,3,0,0,"default"],[58200,2,0,0,"default"],[58300,5,0,0,"default"],[58400,7,0,0,"default"],[58500,0,0,0,"default"],[58600,3,0,0,"default"],[58800,5,0,0,"default"],[58900,1,0,0,"default"],[59000,5,0,0,"default"],[59100,2,0,0,"default"]],"altAnim":false,"bpm":150,"changeBPM":false,"mustHitSection":false},{"lengthInSteps":16,"typeOfSection":0,"sectionNotes":[[59200,3,0,0,"default"],[59300,6,0,0,"default"],[59400,7,0,0,"default"],[59500,4,0,0,"default"],[59600,2,0,0,"default"],[59700,0,0,0,"default"],[59800,5,0,0,"default"],[59900,1,0,0,"default"],[60000,7,0,0,"default"],[60050,6,0,0,"default"],[60100,4,0,0,"default"],[60150,2,0,0,"default"],[60200,5,0,0,"default"],[60250,3,0,0,"default"],[60300,1,0,0,"default"],[60350,0,0,0,"default"],[60400,7,0,0,"default"],[60450,6,0,0,"default"],[60500,4,0,0,"default"],[60550,2,0,0,"default"],[60600,5,0,0,"default"],[60650,3,0,0,"default"],[60700,1,0,0,"default"],[60750,0,0,0,"default"]],"altAnim":false,"bpm":150,"changeBPM":false,"mustHitSection":false},{"lengthInSteps":16,"typeOfSection":0,"sectionNotes":[[60800,12,300,0,"default"],[60800,3,0,0,"default"],[60900,5,0,0,"default"],[61000,6,0,0,"default"],[61100,1,0,0,"default"],[61200,4,0,0,"default"],[61300,3,0,0,"default"],[61400,2,0,0,"default"],[61500,5,0,0,"default"],[61600,7,0,0,"default"],[61700,0,0,0,"default"],[61800,3,0,0,"default"],[62000,5,0,0,"default"],[62100,1,0,0,"default"],[62200,5,0,0,"default"],[62300,2,0,0,"default"]],"altAnim":false,"bpm":150,"changeBPM":false,"mustHitSection":true},{"lengthInSteps":16,"typeOfSection":0,"sectionNotes":[[62400,3,0,0,"default"],[62500,6,0,0,"default"],[62600,7,0,0,"default"],[62700,4,0,0,"default"],[62800,2,0,0,"default"],[62900,0,0,0,"default"],[63000,5,0,0,"default"],[63100,1,0,0,"default"],[63200,7,0,0,"default"],[63250,6,0,0,"default"],[63300,4,0,0,"default"],[63350,2,0,0,"default"],[63400,5,0,0,"default"],[63450,3,0,0,"default"],[63500,1,0,0,"default"],[63550,0,0,0,"default"],[63600,7,0,0,"default"],[63650,6,0,0,"default"],[63700,4,0,0,"default"],[63750,2,0,0,"default"],[63800,5,0,0,"default"],[63850,3,0,0,"default"],[63900,1,0,0,"default"],[63950,0,0,0,"default"]],"altAnim":false,"bpm":150,"changeBPM":false,"mustHitSection":true},{"lengthInSteps":16,"typeOfSection":0,"sectionNotes":[[64000,12,300,0,"default"],[64000,2,0,0,"default"],[64100,7,0,0,"default"],[64300,7,0,0,"default"],[64200,6,0,0,"default"],[64400,4,100,0,"default"],[64600,1,0,0,"default"],[64800,3,0,0,"default"],[64900,1,0,0,"default"],[65000,4,0,0,"default"],[65100,3,0,0,"default"],[65200,0,0,0,"default"],[65300,2,0,0,"default"],[65400,7,0,0,"default"],[65500,5,0,0,"default"]],"altAnim":false,"bpm":150,"changeBPM":false,"mustHitSection":false},{"lengthInSteps":16,"typeOfSection":0,"sectionNotes":[[65600,4,0,0,"default"],[65700,6,0,0,"default"],[65800,1,0,0,"default"],[65900,7,0,0,"default"],[66000,3,0,0,"default"],[66100,2,0,0,"default"],[66200,5,0,0,"default"],[66300,0,0,0,"default"],[66400,4,100,0,"default"],[66600,6,100,0,"default"],[66900,0,0,0,"default"],[67100,0,0,0,"default"],[66800,2,0,0,"default"],[67000,7,0,0,"default"]],"altAnim":false,"bpm":150,"changeBPM":false,"mustHitSection":false},{"lengthInSteps":16,"typeOfSection":0,"sectionNotes":[[67200,11,300,0,"default"],[67200,2,0,0,"default"],[67300,7,0,0,"default"],[67500,7,0,0,"default"],[67400,6,0,0,"default"],[67600,4,100,0,"default"],[67800,1,0,0,"default"],[68000,3,0,0,"default"],[68100,1,0,0,"default"],[68200,4,0,0,"default"],[68300,3,0,0,"default"],[68400,0,0,0,"default"],[68500,2,0,0,"default"],[68600,7,0,0,"default"],[68700,5,0,0,"default"]],"altAnim":false,"bpm":150,"changeBPM":false,"mustHitSection":true},{"lengthInSteps":16,"typeOfSection":0,"sectionNotes":[[68800,4,0,0,"default"],[68900,6,0,0,"default"],[69000,1,0,0,"default"],[69100,7,0,0,"default"],[69200,3,0,0,"default"],[69300,2,0,0,"default"],[69400,5,0,0,"default"],[69500,0,0,0,"default"],[69600,4,100,0,"default"],[69800,6,100,0,"default"],[70100,0,0,0,"default"],[70300,0,0,0,"default"],[70000,2,0,0,"default"],[70200,7,0,0,"default"]],"altAnim":false,"bpm":150,"changeBPM":false,"mustHitSection":true},{"lengthInSteps":16,"typeOfSection":0,"sectionNotes":[[70400,11,300,0,"default"],[70600,4,0,0,"default"],[70800,6,0,0,"default"],[70900,5,0,0,"default"],[70400,2,100,0,"default"],[71000,2,100,0,"default"],[71200,7,0,0,"default"],[71400,4,0,0,"default"],[71600,1,0,0,"default"],[71700,5,0,0,"default"],[71800,3,0,0,"default"],[71900,0,0,0,"default"]],"altAnim":false,"bpm":150,"changeBPM":false,"mustHitSection":false},{"lengthInSteps":16,"typeOfSection":0,"sectionNotes":[[72200,4,0,0,"default"],[72400,6,0,0,"default"],[72500,5,0,0,"default"],[72000,2,100,0,"default"],[72600,2,100,0,"default"],[72800,7,0,0,"default"],[73000,4,0,0,"default"],[73200,1,0,0,"default"],[73300,5,0,0,"default"],[73400,3,0,0,"default"],[73500,0,0,0,"default"]],"altAnim":false,"bpm":150,"changeBPM":false,"mustHitSection":true},{"lengthInSteps":16,"typeOfSection":0,"sectionNotes":[[73600,4,0,0,"default"],[73700,6,0,0,"default"],[73800,4,0,0,"default"],[74000,2,100,0,"default"],[74200,1,100,0,"default"],[74400,7,0,0,"default"],[74500,5,0,0,"default"],[74600,4,0,0,"default"],[74700,2,0,0,"default"],[74800,6,0,0,"default"],[74900,3,0,0,"default"],[75000,1,0,0,"default"],[75100,0,0,0,"default"]],"altAnim":false,"bpm":150,"changeBPM":false,"mustHitSection":false},{"lengthInSteps":16,"typeOfSection":0,"sectionNotes":[[75200,4,0,0,"default"],[75300,6,0,0,"default"],[75400,4,0,0,"default"],[75600,2,100,0,"default"],[75800,1,100,0,"default"],[76000,7,0,0,"default"],[76100,5,0,0,"default"],[76200,4,0,0,"default"],[76300,2,0,0,"default"],[76400,6,0,0,"default"],[76500,3,0,0,"default"],[76600,1,0,0,"default"],[76700,0,0,0,"default"]],"altAnim":false,"bpm":150,"changeBPM":false,"mustHitSection":true},{"lengthInSteps":16,"typeOfSection":0,"sectionNotes":[[76800,6,0,0,"default"],[76900,2,0,0,"default"],[77000,1,0,0,"default"],[77100,4,0,0,"default"],[77200,3,100,0,"default"],[77400,6,0,0,"default"],[77600,7,0,0,"default"],[77700,4,0,0,"default"],[77800,2,0,0,"default"],[77900,5,0,0,"default"],[78000,6,0,0,"default"],[78100,2,0,0,"default"],[78200,5,0,0,"default"],[78300,1,0,0,"default"]],"altAnim":false,"bpm":150,"changeBPM":false,"mustHitSection":false},{"lengthInSteps":16,"typeOfSection":0,"sectionNotes":[[78400,6,0,0,"default"],[78500,2,0,0,"default"],[78600,1,0,0,"default"],[78700,4,0,0,"default"],[78800,3,100,0,"default"],[79000,6,0,0,"default"],[79200,7,0,0,"default"],[79300,4,0,0,"default"],[79400,2,0,0,"default"],[79500,5,0,0,"default"],[79600,6,0,0,"default"],[79700,2,0,0,"default"],[79800,5,0,0,"default"],[79900,1,0,0,"default"]],"altAnim":false,"bpm":150,"changeBPM":false,"mustHitSection":true},{"lengthInSteps":16,"typeOfSection":0,"sectionNotes":[[80000,3,100,0,"default"],[80200,6,0,0,"default"],[80400,5,100,0,"default"],[80600,0,0,0,"default"],[80800,2,300,0,"default"],[81200,6,0,0,"default"],[81300,3,0,0,"default"],[81400,4,0,0,"default"],[81500,5,0,0,"default"]],"altAnim":false,"bpm":150,"changeBPM":false,"mustHitSection":false},{"lengthInSteps":16,"typeOfSection":0,"sectionNotes":[[81600,3,100,0,"default"],[81800,6,0,0,"default"],[82000,5,100,0,"default"],[82200,0,0,0,"default"],[82400,2,300,0,"default"],[82800,6,0,0,"default"],[82900,3,0,0,"default"],[83000,4,0,0,"default"],[83100,5,0,0,"default"],[81600,15,700,0,"default"]],"altAnim":false,"bpm":150,"changeBPM":false,"mustHitSection":true},{"lengthInSteps":16,"typeOfSection":0,"sectionNotes":[[83200,15,700,0,"default"],[83200,3,0,0,"default"],[83300,5,0,0,"default"],[83400,6,0,0,"default"],[83500,1,0,0,"default"],[83600,4,0,0,"default"],[83700,3,0,0,"default"],[83800,2,0,0,"default"],[83900,5,0,0,"default"],[84000,7,0,0,"default"],[84100,0,0,0,"default"],[84200,3,0,0,"default"],[84400,5,0,0,"default"],[84500,1,0,0,"default"],[84600,5,0,0,"default"],[84700,2,0,0,"default"]],"altAnim":false,"bpm":150,"changeBPM":false,"mustHitSection":false},{"lengthInSteps":16,"typeOfSection":0,"sectionNotes":[[84800,3,0,0,"default"],[84900,5,0,0,"default"],[85000,6,0,0,"default"],[85100,1,0,0,"default"],[85200,4,0,0,"default"],[85300,3,0,0,"default"],[85400,2,0,0,"default"],[85500,5,0,0,"default"],[85600,7,0,0,"default"],[85700,0,0,0,"default"],[85800,3,0,0,"default"],[86000,5,0,0,"default"],[86100,1,0,0,"default"],[86200,5,0,0,"default"],[86300,2,0,0,"default"]],"altAnim":false,"bpm":150,"changeBPM":false,"mustHitSection":true},{"lengthInSteps":16,"typeOfSection":0,"sectionNotes":[[86400,3,0,0,"default"],[86500,6,0,0,"default"],[86600,7,0,0,"default"],[86700,4,0,0,"default"],[86800,2,0,0,"default"],[86900,0,0,0,"default"],[87000,5,0,0,"default"],[87100,1,0,0,"default"],[87200,7,0,0,"default"],[87250,6,0,0,"default"],[87300,4,0,0,"default"],[87350,2,0,0,"default"],[87400,5,0,0,"default"],[87450,3,0,0,"default"],[87500,1,0,0,"default"],[87550,0,0,0,"default"],[87600,7,0,0,"default"],[87650,6,0,0,"default"],[87700,4,0,0,"default"],[87750,2,0,0,"default"],[87800,5,0,0,"default"],[87850,3,0,0,"default"],[87900,1,0,0,"default"],[87950,0,0,0,"default"]],"altAnim":false,"bpm":150,"changeBPM":false,"mustHitSection":false},{"lengthInSteps":16,"typeOfSection":0,"sectionNotes":[[88000,3,0,0,"default"],[88100,6,0,0,"default"],[88200,7,0,0,"default"],[88300,4,0,0,"default"],[88400,2,0,0,"default"],[88500,0,0,0,"default"],[88600,5,0,0,"default"],[88700,1,0,0,"default"],[88800,7,0,0,"default"],[88850,6,0,0,"default"],[88900,4,0,0,"default"],[88950,2,0,0,"default"],[89000,5,0,0,"default"],[89050,3,0,0,"default"],[89100,1,0,0,"default"],[89150,0,0,0,"default"],[89200,7,0,0,"default"],[89250,6,0,0,"default"],[89300,4,0,0,"default"],[89350,2,0,0,"default"],[89400,5,0,0,"default"],[89450,3,0,0,"default"],[89500,1,0,0,"default"],[89550,0,0,0,"default"]],"altAnim":false,"bpm":150,"changeBPM":false,"mustHitSection":true},{"lengthInSteps":16,"typeOfSection":0,"sectionNotes":[[89600,2,0,0,"default"],[89700,7,0,0,"default"],[89900,7,0,0,"default"],[89800,6,0,0,"default"],[90000,4,100,0,"default"],[90200,1,0,0,"default"],[90400,3,0,0,"default"],[90500,1,0,0,"default"],[90600,4,0,0,"default"],[90700,3,0,0,"default"],[90800,0,0,0,"default"],[90900,2,0,0,"default"],[91000,7,0,0,"default"],[91100,5,0,0,"default"]],"altAnim":false,"bpm":150,"changeBPM":false,"mustHitSection":false},{"lengthInSteps":16,"typeOfSection":0,"sectionNotes":[[91200,2,0,0,"default"],[91300,7,0,0,"default"],[91500,7,0,0,"default"],[91400,6,0,0,"default"],[91600,4,100,0,"default"],[91800,1,0,0,"default"],[92000,3,0,0,"default"],[92100,1,0,0,"default"],[92200,4,0,0,"default"],[92300,3,0,0,"default"],[92400,0,0,0,"default"],[92500,2,0,0,"default"],[92600,7,0,0,"default"],[92700,5,0,0,"default"]],"altAnim":false,"bpm":150,"changeBPM":false,"mustHitSection":true},{"lengthInSteps":16,"typeOfSection":0,"sectionNotes":[[92800,4,0,0,"default"],[92900,6,0,0,"default"],[93000,1,0,0,"default"],[93100,7,0,0,"default"],[93200,3,0,0,"default"],[93300,2,0,0,"default"],[93400,5,0,0,"default"],[93500,0,0,0,"default"],[93600,4,100,0,"default"],[93800,6,100,0,"default"],[94100,0,0,0,"default"],[94300,0,0,0,"default"],[94000,2,0,0,"default"],[94200,7,0,0,"default"]],"altAnim":false,"bpm":150,"changeBPM":false,"mustHitSection":false},{"lengthInSteps":16,"typeOfSection":0,"sectionNotes":[[94400,4,0,0,"default"],[94500,6,0,0,"default"],[94600,1,0,0,"default"],[94700,7,0,0,"default"],[94800,3,0,0,"default"],[94900,2,0,0,"default"],[95000,5,0,0,"default"],[95100,0,0,0,"default"],[95200,4,100,0,"default"],[95400,6,100,0,"default"],[95700,0,0,0,"default"],[95900,0,0,0,"default"],[95600,2,0,0,"default"],[95800,7,0,0,"default"]],"altAnim":false,"bpm":150,"changeBPM":false,"mustHitSection":true},{"lengthInSteps":16,"typeOfSection":0,"sectionNotes":[[96000,5,700,0,"default"],[96000,2,700,0,"default"],[96000,10,700,0,"default"],[96000,13,700,0,"default"]],"altAnim":false,"bpm":150,"changeBPM":false,"mustHitSection":true},{"lengthInSteps":16,"typeOfSection":0,"sectionNotes":[],"altAnim":false,"bpm":150,"changeBPM":false,"mustHitSection":true},{"lengthInSteps":16,"typeOfSection":0,"sectionNotes":[],"altAnim":false,"bpm":150,"changeBPM":false,"mustHitSection":true},{"lengthInSteps":16,"typeOfSection":0,"sectionNotes":[],"altAnim":false,"bpm":150,"changeBPM":false,"mustHitSection":true},{"sectionNotes":[],"typeOfSection":0,"lengthInSteps":16,"altAnim":false,"mustHitSection":true,"changeBPM":false,"bpm":150},{"lengthInSteps":16,"altAnim":false,"changeTimeScale":false,"typeOfSection":0,"sectionNotes":[],"bpm":150,"changeBPM":false,"timeScale":[4,4],"mustHitSection":true},{"lengthInSteps":16,"altAnim":false,"changeTimeScale":false,"typeOfSection":0,"sectionNotes":[],"bpm":150,"changeBPM":false,"timeScale":[4,4],"mustHitSection":true},{"lengthInSteps":16,"altAnim":false,"changeTimeScale":false,"typeOfSection":0,"sectionNotes":[],"bpm":150,"changeBPM":false,"timeScale":[4,4],"mustHitSection":true},{"lengthInSteps":16,"altAnim":false,"changeTimeScale":false,"typeOfSection":0,"sectionNotes":[],"bpm":150,"changeBPM":false,"timeScale":[4,4],"mustHitSection":true}],"playerKeyCount":8,"mania":null,"endCutscene":"","song":"collapse","validScore":true,"speed":2.4,"sectionLengths":[],"ui_Skin":"default","events":[],"cutscene":"","timescale":[4,4],"needsVoices":false,"sections":0,"stage":"shaggy-godeater","gf":"gf","bpm":150}}